SNS_diffusion_simulator.py
SNS_diffusion_simulator-0.0.1.dist-info/METADATA
SNS_diffusion_simulator-0.0.1.dist-info/WHEEL
SNS_diffusion_simulator-0.0.1.dist-info/entry_points.txt
SNS_diffusion_simulator-0.0.1.dist-info/top_level.txt
SNS_diffusion_simulator-0.0.1.dist-info/RECORD
