Metadata-Version: 2.1
Name: SNS-diffusion-simulator
Version: 0.0.1
Summary: Simulator for estimating the spread of SNS
Home-page: https://github.com/umeryu1121ac/diffusion_sim.git
Author: umeryu1121ac
Author-email: s2122007@stu.musashino-u.ac.jp
License: UNKNOWN
Project-URL: Bug Tracker, https://github.com/umeryu1121ac/diffusion_sim.git
Platform: UNKNOWN
Classifier: Programming Language :: Python :: 3
Classifier: License :: OSI Approved :: MIT License
Classifier: Operating System :: OS Independent
Requires-Python: >=3.7
